gridappsd_field_bus/__init__.py
gridappsd_field_bus/field_interface/__init__.py
gridappsd_field_bus/field_interface/agents/__init__.py
gridappsd_field_bus/field_interface/agents/agents.py
gridappsd_field_bus/field_interface/context.py
gridappsd_field_bus/field_interface/context_managers/__init__.py
gridappsd_field_bus/field_interface/context_managers/centralized_context_managers.py
gridappsd_field_bus/field_interface/context_managers/context_manager_agents.py
gridappsd_field_bus/field_interface/context_managers/substation.py
gridappsd_field_bus/field_interface/context_managers/utils.py
gridappsd_field_bus/field_interface/field_proxy_forwarder.py
gridappsd_field_bus/field_interface/gridappsd_field_bus.py
gridappsd_field_bus/field_interface/interfaces.py
gridappsd_field_bus/forwarder.py
gridappsd_field_bus-2025.3.1.dist-info/METADATA
gridappsd_field_bus-2025.3.1.dist-info/WHEEL
gridappsd_field_bus-2025.3.1.dist-info/entry_points.txt
gridappsd_field_bus-2025.3.1.dist-info/RECORD
