Metadata-Version: 2.3
Name: gridappsd-field-bus
Version: 2025.3.1
Summary: GridAPPS-D Field Bus Implementation
License: BSD-3-Clause
Keywords: gridappsd,grid,activemq,powergrid,simulation,library
Author: C. Allwardt
Author-email: 3979063+craig8@users.noreply.github.com
Requires-Python: >=3.10,<4.0
Classifier: License :: OSI Approved :: BSD License
Classifier: Programming Language :: Python :: 3
Classifier: Programming Language :: Python :: 3.10
Classifier: Programming Language :: Python :: 3.11
Classifier: Programming Language :: Python :: 3.12
Classifier: Programming Language :: Python :: 3.13
Requires-Dist: cim-graph (>=0.2.2a4)
Requires-Dist: click (>=8.1.8,<9.0.0)
Requires-Dist: gridappsd-python (>=2025.3.1a1)
Requires-Dist: python-dotenv (>=1.0.1,<2.0.0)
Project-URL: Homepage, https://gridappsd.readthedocs.io
Project-URL: Repository, https://github.com/GRIDAPPSD/gridappsd-python
